cvnn_utils/__init__.py
cvnn_utils/activations.py
cvnn_utils/initialization.py
cvnn_utils/layers.py
cvnn_utils/optimizer.py
cvnn_utils/utils.py
cvnn_utils-0.1.10.dist-info/licenses/LICENSE
cvnn_utils-0.1.10.dist-info/METADATA
cvnn_utils-0.1.10.dist-info/WHEEL
cvnn_utils-0.1.10.dist-info/top_level.txt
cvnn_utils-0.1.10.dist-info/RECORD
