Metadata-Version: 2.4
Name: cvnn-utils
Version: 0.1.10
Summary: A lightweight, principled toolkit for Complex-Valued Neural Networks in PyTorch.
Home-page: https://github.com/KrisTHL181/cvnn-utils
Author: KrisTHL181
License: MIT
Keywords: deep learning,complex-valued,neural network,cvnn,pytorch
Classifier: Development Status :: 3 - Alpha
Classifier: Intended Audience :: Science/Research
Classifier: Topic :: Scientific/Engineering :: Artificial Intelligence
Classifier: License :: OSI Approved :: MIT License
Classifier: Programming Language :: Python :: 3
Classifier: Programming Language :: Python :: 3.8
Classifier: Programming Language :: Python :: 3.9
Classifier: Programming Language :: Python :: 3.10
Requires-Python: >=3.8
License-File: LICENSE
Requires-Dist: torch>=1.8.0
Dynamic: author
Dynamic: classifier
Dynamic: description
Dynamic: description-content-type
Dynamic: home-page
Dynamic: keywords
Dynamic: license
Dynamic: license-file
Dynamic: requires-dist
Dynamic: requires-python
Dynamic: summary
